trustauthx/__init__.py
trustauthx/authlite.py
trustauthx/cli.py
trustauthx/llmai.py
trustauthx/scheme.py
trustauthx-1.3.0.dist-info/licenses/LICENSE
trustauthx-1.3.0.dist-info/METADATA
trustauthx-1.3.0.dist-info/WHEEL
trustauthx-1.3.0.dist-info/entry_points.txt
trustauthx-1.3.0.dist-info/top_level.txt
trustauthx-1.3.0.dist-info/RECORD
