Metadata-Version: 2.4
Name: trustauthx
Version: 1.3.0
Summary: Official connector SDK for TrustAuthx
Home-page: https://github.com/One-Click-Auth/TrustAuthx-Py-SDK.git
Author: moonlightnexus
Author-email: nexus@trustauthx.com
License: MIT
Classifier: Development Status :: 4 - Beta
Classifier: Intended Audience :: Developers
Classifier: License :: OSI Approved :: MIT License
Classifier: Programming Language :: Python :: 3.9
License-File: LICENSE
Requires-Dist: certifi>=2023.5.7
Requires-Dist: cffi>=1.15.1
Requires-Dist: cryptography>=3.4.10
Requires-Dist: ecdsa>=0.18.0
Requires-Dist: idna>=3.4
Requires-Dist: pyasn1>=0.5.0
Requires-Dist: pycparser>=2.21
Requires-Dist: requests>=2.31.0
Requires-Dist: rsa>=4.9
Requires-Dist: six>=1.16.0
Requires-Dist: urllib3<=3.0.0
Requires-Dist: charset-normalizer>=3.2.0
Requires-Dist: python-jose>=3.3.0
Requires-Dist: python-dotenv>=1.0.0
Requires-Dist: fissix==24.4.24
Dynamic: author
Dynamic: author-email
Dynamic: classifier
Dynamic: description
Dynamic: description-content-type
Dynamic: home-page
Dynamic: license
Dynamic: license-file
Dynamic: requires-dist
Dynamic: summary
